murmur/build/__init__.py
murmur/build/activate_agent.py
murmur/utils/__init__.py
murmur/utils/client_options.py
murmur/utils/enums.py
murmur/utils/instructions_handler.py
murmur/utils/logging_config.py
murmur_slim-0.0.4.dist-info/METADATA
murmur_slim-0.0.4.dist-info/WHEEL
murmur_slim-0.0.4.dist-info/RECORD
